streamdiffer
