Metadata-Version: 1.0
Name: StreamDiffer
Version: 0.0.2
Summary: Compare and clusterize multiple data streams.
Home-page: https://github.com/nilp0inter/streamdiffer
Author: Roberto Abdelkader Martínez Pérez
Author-email: robertomartinezp@gmail.com
License: UNKNOWN
Platform: UNKNOWN
